jetdiff/__init__.py
jetdiff/jet.py
jetdiff-0.0.1.dist-info/LICENSE
jetdiff-0.0.1.dist-info/METADATA
jetdiff-0.0.1.dist-info/WHEEL
jetdiff-0.0.1.dist-info/top_level.txt
jetdiff-0.0.1.dist-info/RECORD
