Metadata-Version: 2.1
Name: jetdiff
Version: 0.0.1
Summary: Simple auto-differentiate helper library
Author: Yienschwen
Project-URL: Homepage, https://github.com/Yienschwen/jetdiff
Classifier: Programming Language :: Python :: 3
Classifier: License :: OSI Approved :: MIT License
Classifier: Operating System :: OS Independent
Requires-Python: >=3.8
License-File: LICENSE
